{
  "duration_ms": 2000,
  "before_score": 86,
  "after_score": 86,
  "score_delta": 0,
  "fixes_attempted": 0,
  "fixes_applied": 0,
  "fixes": [],
  "comparison": {
    "score_before": 86,
    "score_after": 86,
    "score_delta": 0,
    "findings_before": 174,
    "findings_after": 174,
    "findings_delta": 0,
    "critical_before": 0,
    "critical_after": 0,
    "coverage_before": 100.0,
    "coverage_after": 100.0,
    "improved": false
  },
  "improvement_summary": {
    "total_files": 175,
    "changed_files": 0,
    "unchanged_files": 175,
    "total_lines_added": 0,
    "total_lines_removed": 0,
    "net_lines": 0,
    "records": [
      {
        "file": "F:/BUREAU/turbo/src/adaptive_router.py",
        "changed": false,
        "lines_before": 384,
        "lines_after": 384,
        "lines_delta": 0,
        "functions_before": 17,
        "functions_after": 17,
        "functions_delta": 0,
        "lines_added": 0,
        "lines_removed": 0,
        "timestamp": 1772893751.5107918
      },
      {
        "file": "F:/BUREAU/turbo/src/agent_auto_scaler.py",
        "changed": false,
        "lines_before": 396,
        "lines_after": 396,
        "lines_delta": 0,
        "functions_before": 10,
        "functions_after": 10,
        "functions_delta": 0,
        "lines_added": 0,
        "lines_removed": 0,
        "timestamp": 1772893751.5112908
      },
      {
        "file": "F:/BUREAU/turbo/src/agent_collaboration.py",
        "changed": false,
        "lines_before": 281,
        "lines_after": 281,
        "lines_delta": 0,
        "functions_before": 7,
        "functions_after": 7,
        "functions_delta": 0,
        "lines_added": 0,
        "lines_removed": 0,
        "timestamp": 1772893751.5112908
      },
      {
        "file": "F:/BUREAU/turbo/src/agent_ensemble.py",
        "changed": false,
        "lines_before": 403,
        "lines_after": 403,
        "lines_delta": 0,
        "functions_before": 11,
        "functions_after": 11,
        "functions_delta": 0,
        "lines_added": 0,
        "lines_removed": 0,
        "timestamp": 1772893751.5122902
      },
      {
        "file": "F:/BUREAU/turbo/src/agent_episodic_memory.py",
        "changed": false,
        "lines_before": 354,
        "lines_after": 354,
        "lines_delta": 0,
        "functions_before": 15,
        "functions_after": 15,
        "functions_delta": 0,
        "lines_added": 0,
        "lines_removed": 0,
        "timestamp": 1772893751.5122902
      },
      {
        "file": "F:/BUREAU/turbo/src/agent_factory.py",
        "changed": false,
        "lines_before": 302,
        "lines_after": 302,
        "lines_delta": 0,
        "functions_before": 8,
        "functions_after": 8,
        "functions_delta": 0,
        "lines_added": 0,
        "lines_removed": 0,
        "timestamp": 1772893751.5127914
      },
      {
        "file": "F:/BUREAU/turbo/src/agent_feedback_loop.py",
        "changed": false,
        "lines_before": 365,
        "lines_after": 365,
        "lines_delta": 0,
        "functions_before": 10,
        "functions_after": 10,
        "functions_delta": 0,
        "lines_added": 0,
        "lines_removed": 0,
        "timestamp": 1772893751.5132914
      },
      {
        "file": "F:/BUREAU/turbo/src/agent_health_guardian.py",
        "changed": false,
        "lines_before": 309,
        "lines_after": 309,
        "lines_delta": 0,
        "functions_before": 6,
        "functions_after": 6,
        "functions_delta": 0,
        "lines_added": 0,
        "lines_removed": 0,
        "timestamp": 1772893751.513791
      },
      {
        "file": "F:/BUREAU/turbo/src/agent_monitor.py",
        "changed": false,
        "lines_before": 270,
        "lines_after": 270,
        "lines_delta": 0,
        "functions_before": 13,
        "functions_after": 13,
        "functions_delta": 0,
        "lines_added": 0,
        "lines_removed": 0,
        "timestamp": 1772893751.513791
      },
      {
        "file": "F:/BUREAU/turbo/src/agent_orchestrator_v3.py",
        "changed": false,
        "lines_before": 432,
        "lines_after": 432,
        "lines_delta": 0,
        "functions_before": 6,
        "functions_after": 6,
        "functions_delta": 0,
        "lines_added": 0,
        "lines_removed": 0,
        "timestamp": 1772893751.5142913
      },
      {
        "file": "F:/BUREAU/turbo/src/agent_prompt_optimizer.py",
        "changed": false,
        "lines_before": 351,
        "lines_after": 351,
        "lines_delta": 0,
        "functions_before": 9,
        "functions_after": 9,
        "functions_delta": 0,
        "lines_added": 0,
        "lines_removed": 0,
        "timestamp": 1772893751.514791
      },
      {
        "file": "F:/BUREAU/turbo/src/agent_self_improve.py",
        "changed": false,
        "lines_before": 404,
        "lines_after": 404,
        "lines_delta": 0,
        "functions_before": 11,
        "functions_after": 11,
        "functions_delta": 0,
        "lines_added": 0,
        "lines_removed": 0,
        "timestamp": 1772893751.5152912
      },
      {
        "file": "F:/BUREAU/turbo/src/agent_task_planner.py",
        "changed": false,
        "lines_before": 337,
        "lines_after": 337,
        "lines_delta": 0,
        "functions_before": 9,
        "functions_after": 9,
        "functions_delta": 0,
        "lines_added": 0,
        "lines_removed": 0,
        "timestamp": 1772893751.5152912
      },
      {
        "file": "F:/BUREAU/turbo/src/alert_manager.py",
        "changed": false,
        "lines_before": 203,
        "lines_after": 203,
        "lines_delta": 0,
        "functions_before": 9,
        "functions_after": 9,
        "functions_delta": 0,
        "lines_added": 0,
        "lines_removed": 0,
        "timestamp": 1772893751.5157912
      },
      {
        "file": "F:/BUREAU/turbo/src/api_gateway.py",
        "changed": false,
        "lines_before": 181,
        "lines_after": 181,
        "lines_delta": 0,
        "functions_before": 8,
        "functions_after": 8,
        "functions_delta": 0,
        "lines_added": 0,
        "lines_removed": 0,
        "timestamp": 1772893751.5157912
      },
      {
        "file": "F:/BUREAU/turbo/src/app_launcher.py",
        "changed": false,
        "lines_before": 220,
        "lines_after": 220,
        "lines_delta": 0,
        "functions_before": 13,
        "functions_after": 13,
        "functions_delta": 0,
        "lines_added": 0,
        "lines_removed": 0,
        "timestamp": 1772893751.5162914
      },
      {
        "file": "F:/BUREAU/turbo/src/audio_controller.py",
        "changed": false,
        "lines_before": 238,
        "lines_after": 238,
        "lines_delta": 0,
        "functions_before": 13,
        "functions_after": 13,
        "functions_delta": 0,
        "lines_added": 0,
        "lines_removed": 0,
        "timestamp": 1772893751.5162914
      },
      {
        "file": "F:/BUREAU/turbo/src/audio_device_manager.py",
        "changed": false,
        "lines_before": 110,
        "lines_after": 110,
        "lines_delta": 0,
        "functions_before": 7,
        "functions_after": 7,
        "functions_delta": 0,
        "lines_added": 0,
        "lines_removed": 0,
        "timestamp": 1772893751.5167913
      },
      {
        "file": "F:/BUREAU/turbo/src/auto_auditor.py",
        "changed": false,
        "lines_before": 406,
        "lines_after": 406,
        "lines_delta": 0,
        "functions_before": 20,
        "functions_after": 20,
        "functions_delta": 0,
        "lines_added": 0,
        "lines_removed": 0,
        "timestamp": 1772893751.5167913
      },
      {
        "file": "F:/BUREAU/turbo/src/auto_developer.py",
        "changed": false,
        "lines_before": 367,
        "lines_after": 367,
        "lines_delta": 0,
        "functions_before": 4,
        "functions_after": 4,
        "functions_delta": 0,
        "lines_added": 0,
        "lines_removed": 0,
        "timestamp": 1772893751.517291
      },
      {
        "file": "F:/BUREAU/turbo/src/auto_scaler.py",
        "changed": false,
        "lines_before": 221,
        "lines_after": 221,
        "lines_delta": 0,
        "functions_before": 2,
        "functions_after": 2,
        "functions_delta": 0,
        "lines_added": 0,
        "lines_removed": 0,
        "timestamp": 1772893751.5177913
      },
      {
        "file": "F:/BUREAU/turbo/src/auto_tune.py",
        "changed": false,
        "lines_before": 201,
        "lines_after": 201,
        "lines_delta": 0,
        "functions_before": 11,
        "functions_after": 11,
        "functions_delta": 0,
        "lines_added": 0,
        "lines_removed": 0,
        "timestamp": 1772893751.5182912
      },
      {
        "file": "F:/BUREAU/turbo/src/autonomous_dev_agent.py",
        "changed": false,
        "lines_before": 458,
        "lines_after": 458,
        "lines_delta": 0,
        "functions_before": 3,
        "functions_after": 3,
        "functions_delta": 0,
        "lines_added": 0,
        "lines_removed": 0,
        "timestamp": 1772893751.5187895
      },
      {
        "file": "F:/BUREAU/turbo/src/autonomous_loop.py",
        "changed": false,
        "lines_before": 716,
        "lines_after": 716,
        "lines_delta": 0,
        "functions_before": 12,
        "functions_after": 12,
        "functions_delta": 0,
        "lines_added": 0,
        "lines_removed": 0,
        "timestamp": 1772893751.5192895
      },
      {
        "file": "F:/BUREAU/turbo/src/bios_settings.py",
        "changed": false,
        "lines_before": 120,
        "lines_after": 120,
        "lines_delta": 0,
        "functions_before": 6,
        "functions_after": 6,
        "functions_delta": 0,
        "lines_added": 0,
        "lines_removed": 0,
        "timestamp": 1772893751.5192895
      },
      {
        "file": "F:/BUREAU/turbo/src/bluetooth_manager.py",
        "changed": false,
        "lines_before": 143,
        "lines_after": 143,
        "lines_delta": 0,
        "functions_before": 8,
        "functions_after": 8,
        "functions_delta": 0,
        "lines_added": 0,
        "lines_removed": 0,
        "timestamp": 1772893751.5192895
      },
      {
        "file": "F:/BUREAU/turbo/src/brain.py",
        "changed": false,
        "lines_before": 652,
        "lines_after": 652,
        "lines_delta": 0,
        "functions_before": 25,
        "functions_after": 25,
        "functions_delta": 0,
        "lines_added": 0,
        "lines_removed": 0,
        "timestamp": 1772893751.5208013
      },
      {
        "file": "F:/BUREAU/turbo/src/browser_navigator.py",
        "changed": false,
        "lines_before": 798,
        "lines_after": 798,
        "lines_delta": 0,
        "functions_before": 5,
        "functions_after": 5,
        "functions_delta": 0,
        "lines_added": 0,
        "lines_removed": 0,
        "timestamp": 1772893751.5213063
      },
      {
        "file": "F:/BUREAU/turbo/src/cache.py",
        "changed": false,
        "lines_before": 263,
        "lines_after": 263,
        "lines_delta": 0,
        "functions_before": 13,
        "functions_after": 13,
        "functions_delta": 0,
        "lines_added": 0,
        "lines_removed": 0,
        "timestamp": 1772893751.5218065
      },
      {
        "file": "F:/BUREAU/turbo/src/certificate_manager.py",
        "changed": false,
        "lines_before": 162,
        "lines_after": 162,
        "lines_delta": 0,
        "functions_before": 9,
        "functions_after": 9,
        "functions_delta": 0,
        "lines_added": 0,
        "lines_removed": 0,
        "timestamp": 1772893751.5218065
      },
      {
        "file": "F:/BUREAU/turbo/src/circuit_breaker.py",
        "changed": false,
        "lines_before": 301,
        "lines_after": 301,
        "lines_delta": 0,
        "functions_before": 17,
        "functions_after": 17,
        "functions_delta": 0,
        "lines_added": 0,
        "lines_removed": 0,
        "timestamp": 1772893751.5223064
      },
      {
        "file": "F:/BUREAU/turbo/src/clipboard_manager.py",
        "changed": false,
        "lines_before": 194,
        "lines_after": 194,
        "lines_delta": 0,
        "functions_before": 13,
        "functions_after": 13,
        "functions_delta": 0,
        "lines_added": 0,
        "lines_removed": 0,
        "timestamp": 1772893751.5228047
      },
      {
        "file": "F:/BUREAU/turbo/src/cluster_intelligence.py",
        "changed": false,
        "lines_before": 422,
        "lines_after": 422,
        "lines_delta": 0,
        "functions_before": 14,
        "functions_after": 14,
        "functions_delta": 0,
        "lines_added": 0,
        "lines_removed": 0,
        "timestamp": 1772893751.5228047
      },
      {
        "file": "F:/BUREAU/turbo/src/cluster_self_healer.py",
        "changed": false,
        "lines_before": 277,
        "lines_after": 277,
        "lines_delta": 0,
        "functions_before": 2,
        "functions_after": 2,
        "functions_delta": 0,
        "lines_added": 0,
        "lines_removed": 0,
        "timestamp": 1772893751.5233066
      },
      {
        "file": "F:/BUREAU/turbo/src/cluster_startup.py",
        "changed": false,
        "lines_before": 813,
        "lines_after": 813,
        "lines_delta": 0,
        "functions_before": 13,
        "functions_after": 13,
        "functions_delta": 0,
        "lines_added": 0,
        "lines_removed": 0,
        "timestamp": 1772893751.5238047
      },
      {
        "file": "F:/BUREAU/turbo/src/code_improvement_tracker.py",
        "changed": false,
        "lines_before": 264,
        "lines_after": 264,
        "lines_delta": 0,
        "functions_before": 20,
        "functions_after": 20,
        "functions_delta": 0,
        "lines_added": 0,
        "lines_removed": 0,
        "timestamp": 1772893751.524304
      },
      {
        "file": "F:/BUREAU/turbo/src/code_review_480b.py",
        "changed": false,
        "lines_before": 365,
        "lines_after": 365,
        "lines_delta": 0,
        "functions_before": 4,
        "functions_after": 4,
        "functions_delta": 0,
        "lines_added": 0,
        "lines_removed": 0,
        "timestamp": 1772893751.5248055
      },
      {
        "file": "F:/BUREAU/turbo/src/collab_bridge.py",
        "changed": false,
        "lines_before": 136,
        "lines_after": 136,
        "lines_delta": 0,
        "functions_before": 10,
        "functions_after": 10,
        "functions_delta": 0,
        "lines_added": 0,
        "lines_removed": 0,
        "timestamp": 1772893751.5248055
      },
      {
        "file": "F:/BUREAU/turbo/src/command_router.py",
        "changed": false,
        "lines_before": 176,
        "lines_after": 176,
        "lines_delta": 0,
        "functions_before": 10,
        "functions_after": 10,
        "functions_delta": 0,
        "lines_added": 0,
        "lines_removed": 0,
        "timestamp": 1772893751.5248055
      },
      {
        "file": "F:/BUREAU/turbo/src/commander.py",
        "changed": false,
        "lines_before": 618,
        "lines_after": 618,
        "lines_delta": 0,
        "functions_before": 21,
        "functions_after": 21,
        "functions_delta": 0,
        "lines_added": 0,
        "lines_removed": 0,
        "timestamp": 1772893751.525802
      },
      {
        "file": "F:/BUREAU/turbo/src/commands.py",
        "changed": false,
        "lines_before": 518,
        "lines_after": 518,
        "lines_delta": 0,
        "functions_before": 18,
        "functions_after": 18,
        "functions_delta": 0,
        "lines_added": 0,
        "lines_removed": 0,
        "timestamp": 1772893751.526304
      },
      {
        "file": "F:/BUREAU/turbo/src/commands_browser.py",
        "changed": false,
        "lines_before": 393,
        "lines_after": 393,
        "lines_delta": 0,
        "functions_before": 0,
        "functions_after": 0,
        "functions_delta": 0,
        "lines_added": 0,
        "lines_removed": 0,
        "timestamp": 1772893751.5268018
      },
      {
        "file": "F:/BUREAU/turbo/src/config.py",
        "changed": false,
        "lines_before": 533,
        "lines_after": 533,
        "lines_delta": 0,
        "functions_before": 16,
        "functions_after": 16,
        "functions_delta": 0,
        "lines_added": 0,
        "lines_removed": 0,
        "timestamp": 1772893751.527303
      },
      {
        "file": "F:/BUREAU/turbo/src/context_manager.py",
        "changed": false,
        "lines_before": 255,
        "lines_after": 255,
        "lines_delta": 0,
        "functions_before": 18,
        "functions_after": 18,
        "functions_delta": 0,
        "lines_added": 0,
        "lines_removed": 0,
        "timestamp": 1772893751.527303
      },
      {
        "file": "F:/BUREAU/turbo/src/cowork_agent_config.py",
        "changed": false,
        "lines_before": 536,
        "lines_after": 536,
        "lines_delta": 0,
        "functions_before": 5,
        "functions_after": 5,
        "functions_delta": 0,
        "lines_added": 0,
        "lines_removed": 0,
        "timestamp": 1772893751.527805
      },
      {
        "file": "F:/BUREAU/turbo/src/cowork_bridge.py",
        "changed": false,
        "lines_before": 382,
        "lines_after": 382,
        "lines_delta": 0,
        "functions_before": 12,
        "functions_after": 12,
        "functions_delta": 0,
        "lines_added": 0,
        "lines_removed": 0,
        "timestamp": 1772893751.5283065
      },
      {
        "file": "F:/BUREAU/turbo/src/cowork_master_config.py",
        "changed": false,
        "lines_before": 435,
        "lines_after": 435,
        "lines_delta": 0,
        "functions_before": 0,
        "functions_after": 0,
        "functions_delta": 0,
        "lines_added": 0,
        "lines_removed": 0,
        "timestamp": 1772893751.5288029
      },
      {
        "file": "F:/BUREAU/turbo/src/cowork_orchestrator.py",
        "changed": false,
        "lines_before": 432,
        "lines_after": 432,
        "lines_delta": 0,
        "functions_before": 7,
        "functions_after": 7,
        "functions_delta": 0,
        "lines_added": 0,
        "lines_removed": 0,
        "timestamp": 1772893751.5288029
      },
      {
        "file": "F:/BUREAU/turbo/src/cowork_proactive.py",
        "changed": false,
        "lines_before": 440,
        "lines_after": 440,
        "lines_delta": 0,
        "functions_before": 17,
        "functions_after": 17,
        "functions_delta": 0,
        "lines_added": 0,
        "lines_removed": 0,
        "timestamp": 1772893751.5293038
      },
      {
        "file": "F:/BUREAU/turbo/src/crash_dump_reader.py",
        "changed": false,
        "lines_before": 150,
        "lines_after": 150,
        "lines_delta": 0,
        "functions_before": 7,
        "functions_after": 7,
        "functions_delta": 0,
        "lines_added": 0,
        "lines_removed": 0,
        "timestamp": 1772893751.5293038
      },
      {
        "file": "F:/BUREAU/turbo/src/credential_vault.py",
        "changed": false,
        "lines_before": 132,
        "lines_after": 132,
        "lines_delta": 0,
        "functions_before": 9,
        "functions_after": 9,
        "functions_delta": 0,
        "lines_added": 0,
        "lines_removed": 0,
        "timestamp": 1772893751.5293038
      },
      {
        "file": "F:/BUREAU/turbo/src/cron_manager.py",
        "changed": false,
        "lines_before": 243,
        "lines_after": 243,
        "lines_delta": 0,
        "functions_before": 13,
        "functions_after": 13,
        "functions_delta": 0,
        "lines_added": 0,
        "lines_removed": 0,
        "timestamp": 1772893751.5293038
      },
      {
        "file": "F:/BUREAU/turbo/src/dashboard.py",
        "changed": false,
        "lines_before": 564,
        "lines_after": 564,
        "lines_delta": 0,
        "functions_before": 15,
        "functions_after": 15,
        "functions_delta": 0,
        "lines_added": 0,
        "lines_removed": 0,
        "timestamp": 1772893751.53031
      },
      {
        "file": "F:/BUREAU/turbo/src/data_pipeline.py",
        "changed": false,
        "lines_before": 169,
        "lines_after": 169,
        "lines_delta": 0,
        "functions_before": 10,
        "functions_after": 10,
        "functions_delta": 0,
        "lines_added": 0,
        "lines_removed": 0,
        "timestamp": 1772893751.5308173
      },
      {
        "file": "F:/BUREAU/turbo/src/data_validator.py",
        "changed": false,
        "lines_before": 264,
        "lines_after": 264,
        "lines_delta": 0,
        "functions_before": 13,
        "functions_after": 13,
        "functions_delta": 0,
        "lines_added": 0,
        "lines_removed": 0,
        "timestamp": 1772893751.5313172
      },
      {
        "file": "F:/BUREAU/turbo/src/database.py",
        "changed": false,
        "lines_before": 759,
        "lines_after": 759,
        "lines_delta": 0,
        "functions_before": 28,
        "functions_after": 28,
        "functions_delta": 0,
        "lines_added": 0,
        "lines_removed": 0,
        "timestamp": 1772893751.5318184
      },
      {
        "file": "F:/BUREAU/turbo/src/defender_status.py",
        "changed": false,
        "lines_before": 148,
        "lines_after": 148,
        "lines_delta": 0,
        "functions_before": 7,
        "functions_after": 7,
        "functions_delta": 0,
        "lines_added": 0,
        "lines_removed": 0,
        "timestamp": 1772893751.5323176
      },
      {
        "file": "F:/BUREAU/turbo/src/disk_health.py",
        "changed": false,
        "lines_before": 150,
        "lines_after": 150,
        "lines_delta": 0,
        "functions_before": 7,
        "functions_after": 7,
        "functions_delta": 0,
        "lines_added": 0,
        "lines_removed": 0,
        "timestamp": 1772893751.5323176
      },
      {
        "file": "F:/BUREAU/turbo/src/disk_monitor.py",
        "changed": false,
        "lines_before": 231,
        "lines_after": 231,
        "lines_delta": 0,
        "functions_before": 11,
        "functions_after": 11,
        "functions_delta": 0,
        "lines_added": 0,
        "lines_removed": 0,
        "timestamp": 1772893751.5323176
      },
      {
        "file": "F:/BUREAU/turbo/src/dispatch_engine.py",
        "changed": false,
        "lines_before": 781,
        "lines_after": 781,
        "lines_delta": 0,
        "functions_before": 13,
        "functions_after": 13,
        "functions_delta": 0,
        "lines_added": 0,
        "lines_removed": 0,
        "timestamp": 1772893751.5338178
      },
      {
        "file": "F:/BUREAU/turbo/src/display_manager.py",
        "changed": false,
        "lines_before": 235,
        "lines_after": 235,
        "lines_delta": 0,
        "functions_before": 11,
        "functions_after": 11,
        "functions_delta": 0,
        "lines_added": 0,
        "lines_removed": 0,
        "timestamp": 1772893751.5343187
      },
      {
        "file": "F:/BUREAU/turbo/src/dns_client_manager.py",
        "changed": false,
        "lines_before": 129,
        "lines_after": 129,
        "lines_delta": 0,
        "functions_before": 7,
        "functions_after": 7,
        "functions_delta": 0,
        "lines_added": 0,
        "lines_removed": 0,
        "timestamp": 1772893751.5343187
      },
      {
        "file": "F:/BUREAU/turbo/src/domino_executor.py",
        "changed": false,
        "lines_before": 1800,
        "lines_after": 1800,
        "lines_delta": 0,
        "functions_before": 126,
        "functions_after": 126,
        "functions_delta": 0,
        "lines_added": 0,
        "lines_removed": 0,
        "timestamp": 1772893751.5368173
      },
      {
        "file": "F:/BUREAU/turbo/src/domino_pipelines.py",
        "changed": false,
        "lines_before": 5850,
        "lines_after": 5850,
        "lines_delta": 0,
        "functions_before": 3,
        "functions_after": 3,
        "functions_delta": 0,
        "lines_added": 0,
        "lines_removed": 0,
        "timestamp": 1772893751.5443242
      },
      {
        "file": "F:/BUREAU/turbo/src/download_manager.py",
        "changed": false,
        "lines_before": 240,
        "lines_after": 240,
        "lines_delta": 0,
        "functions_before": 14,
        "functions_after": 14,
        "functions_delta": 0,
        "lines_added": 0,
        "lines_removed": 0,
        "timestamp": 1772893751.5443242
      },
      {
        "file": "F:/BUREAU/turbo/src/driver_manager.py",
        "changed": false,
        "lines_before": 135,
        "lines_after": 135,
        "lines_delta": 0,
        "functions_before": 8,
        "functions_after": 8,
        "functions_delta": 0,
        "lines_added": 0,
        "lines_removed": 0,
        "timestamp": 1772893751.544823
      },
      {
        "file": "F:/BUREAU/turbo/src/dynamic_agents.py",
        "changed": false,
        "lines_before": 308,
        "lines_after": 308,
        "lines_delta": 0,
        "functions_before": 9,
        "functions_after": 9,
        "functions_delta": 0,
        "lines_added": 0,
        "lines_removed": 0,
        "timestamp": 1772893751.544823
      },
      {
        "file": "F:/BUREAU/turbo/src/email_sender.py",
        "changed": false,
        "lines_before": 286,
        "lines_after": 286,
        "lines_delta": 0,
        "functions_before": 16,
        "functions_after": 16,
        "functions_delta": 0,
        "lines_added": 0,
        "lines_removed": 0,
        "timestamp": 1772893751.5453243
      },
      {
        "file": "F:/BUREAU/turbo/src/env_variable_manager.py",
        "changed": false,
        "lines_before": 157,
        "lines_after": 157,
        "lines_delta": 0,
        "functions_before": 10,
        "functions_after": 10,
        "functions_delta": 0,
        "lines_added": 0,
        "lines_removed": 0,
        "timestamp": 1772893751.5453243
      },
      {
        "file": "F:/BUREAU/turbo/src/event_store.py",
        "changed": false,
        "lines_before": 145,
        "lines_after": 145,
        "lines_delta": 0,
        "functions_before": 15,
        "functions_after": 15,
        "functions_delta": 0,
        "lines_added": 0,
        "lines_removed": 0,
        "timestamp": 1772893751.5458248
      },
      {
        "file": "F:/BUREAU/turbo/src/event_stream.py",
        "changed": false,
        "lines_before": 239,
        "lines_after": 239,
        "lines_delta": 0,
        "functions_before": 14,
        "functions_after": 14,
        "functions_delta": 0,
        "lines_added": 0,
        "lines_removed": 0,
        "timestamp": 1772893751.5458248
      },
      {
        "file": "F:/BUREAU/turbo/src/eventlog_reader.py",
        "changed": false,
        "lines_before": 162,
        "lines_after": 162,
        "lines_delta": 0,
        "functions_before": 9,
        "functions_after": 9,
        "functions_delta": 0,
        "lines_added": 0,
        "lines_removed": 0,
        "timestamp": 1772893751.5463235
      },
      {
        "file": "F:/BUREAU/turbo/src/exchanges.py",
        "changed": false,
        "lines_before": 317,
        "lines_after": 317,
        "lines_delta": 0,
        "functions_before": 10,
        "functions_after": 10,
        "functions_delta": 0,
        "lines_added": 0,
        "lines_removed": 0,
        "timestamp": 1772893751.5463235
      },
      {
        "file": "F:/BUREAU/turbo/src/executor.py",
        "changed": false,
        "lines_before": 623,
        "lines_after": 623,
        "lines_delta": 0,
        "functions_before": 10,
        "functions_after": 10,
        "functions_delta": 0,
        "lines_added": 0,
        "lines_removed": 0,
        "timestamp": 1772893751.547324
      },
      {
        "file": "F:/BUREAU/turbo/src/file_watcher.py",
        "changed": false,
        "lines_before": 282,
        "lines_after": 282,
        "lines_delta": 0,
        "functions_before": 13,
        "functions_after": 13,
        "functions_delta": 0,
        "lines_added": 0,
        "lines_removed": 0,
        "timestamp": 1772893751.547324
      },
      {
        "file": "F:/BUREAU/turbo/src/firewall_controller.py",
        "changed": false,
        "lines_before": 187,
        "lines_after": 187,
        "lines_delta": 0,
        "functions_before": 10,
        "functions_after": 10,
        "functions_delta": 0,
        "lines_added": 0,
        "lines_removed": 0,
        "timestamp": 1772893751.5478234
      },
      {
        "file": "F:/BUREAU/turbo/src/font_manager.py",
        "changed": false,
        "lines_before": 167,
        "lines_after": 167,
        "lines_delta": 0,
        "functions_before": 10,
        "functions_after": 10,
        "functions_delta": 0,
        "lines_added": 0,
        "lines_removed": 0,
        "timestamp": 1772893751.5478234
      },
      {
        "file": "F:/BUREAU/turbo/src/gpu_guardian.py",
        "changed": false,
        "lines_before": 287,
        "lines_after": 287,
        "lines_delta": 0,
        "functions_before": 7,
        "functions_after": 7,
        "functions_delta": 0,
        "lines_added": 0,
        "lines_removed": 0,
        "timestamp": 1772893751.5483234
      },
      {
        "file": "F:/BUREAU/turbo/src/gpu_monitor.py",
        "changed": false,
        "lines_before": 180,
        "lines_after": 180,
        "lines_delta": 0,
        "functions_before": 8,
        "functions_after": 8,
        "functions_delta": 0,
        "lines_added": 0,
        "lines_removed": 0,
        "timestamp": 1772893751.5483234
      },
      {
        "file": "F:/BUREAU/turbo/src/group_policy_reader.py",
        "changed": false,
        "lines_before": 157,
        "lines_after": 157,
        "lines_delta": 0,
        "functions_before": 8,
        "functions_after": 8,
        "functions_delta": 0,
        "lines_added": 0,
        "lines_removed": 0,
        "timestamp": 1772893751.5488234
      },
      {
        "file": "F:/BUREAU/turbo/src/health_dashboard.py",
        "changed": false,
        "lines_before": 177,
        "lines_after": 177,
        "lines_delta": 0,
        "functions_before": 4,
        "functions_after": 4,
        "functions_delta": 0,
        "lines_added": 0,
        "lines_removed": 0,
        "timestamp": 1772893751.5493238
      },
      {
        "file": "F:/BUREAU/turbo/src/health_probe.py",
        "changed": false,
        "lines_before": 171,
        "lines_after": 171,
        "lines_delta": 0,
        "functions_before": 10,
        "functions_after": 10,
        "functions_delta": 0,
        "lines_added": 0,
        "lines_removed": 0,
        "timestamp": 1772893751.5493238
      },
      {
        "file": "F:/BUREAU/turbo/src/hosts_manager.py",
        "changed": false,
        "lines_before": 142,
        "lines_after": 142,
        "lines_delta": 0,
        "functions_before": 9,
        "functions_after": 9,
        "functions_delta": 0,
        "lines_added": 0,
        "lines_removed": 0,
        "timestamp": 1772893751.5493238
      },
      {
        "file": "F:/BUREAU/turbo/src/hotfix_manager.py",
        "changed": false,
        "lines_before": 117,
        "lines_after": 117,
        "lines_delta": 0,
        "functions_before": 8,
        "functions_after": 8,
        "functions_delta": 0,
        "lines_added": 0,
        "lines_removed": 0,
        "timestamp": 1772893751.5493238
      },
      {
        "file": "F:/BUREAU/turbo/src/ia_tool_executor.py",
        "changed": false,
        "lines_before": 357,
        "lines_after": 357,
        "lines_delta": 0,
        "functions_before": 6,
        "functions_after": 6,
        "functions_delta": 0,
        "lines_added": 0,
        "lines_removed": 0,
        "timestamp": 1772893751.5503304
      },
      {
        "file": "F:/BUREAU/turbo/src/installed_apps_manager.py",
        "changed": false,
        "lines_before": 148,
        "lines_after": 148,
        "lines_delta": 0,
        "functions_before": 8,
        "functions_after": 8,
        "functions_delta": 0,
        "lines_added": 0,
        "lines_removed": 0,
        "timestamp": 1772893751.5508366
      },
      {
        "file": "F:/BUREAU/turbo/src/ip_config_manager.py",
        "changed": false,
        "lines_before": 169,
        "lines_after": 169,
        "lines_delta": 0,
        "functions_before": 9,
        "functions_after": 9,
        "functions_delta": 0,
        "lines_added": 0,
        "lines_removed": 0,
        "timestamp": 1772893751.5508366
      },
      {
        "file": "F:/BUREAU/turbo/src/local_security_policy.py",
        "changed": false,
        "lines_before": 126,
        "lines_after": 126,
        "lines_delta": 0,
        "functions_before": 8,
        "functions_after": 8,
        "functions_delta": 0,
        "lines_added": 0,
        "lines_removed": 0,
        "timestamp": 1772893751.5513365
      },
      {
        "file": "F:/BUREAU/turbo/src/locale_manager.py",
        "changed": false,
        "lines_before": 184,
        "lines_after": 184,
        "lines_delta": 0,
        "functions_before": 9,
        "functions_after": 9,
        "functions_delta": 0,
        "lines_added": 0,
        "lines_removed": 0,
        "timestamp": 1772893751.5518353
      },
      {
        "file": "F:/BUREAU/turbo/src/logging_config.py",
        "changed": false,
        "lines_before": 216,
        "lines_after": 216,
        "lines_delta": 0,
        "functions_before": 8,
        "functions_after": 8,
        "functions_delta": 0,
        "lines_added": 0,
        "lines_removed": 0,
        "timestamp": 1772893751.5523353
      },
      {
        "file": "F:/BUREAU/turbo/src/mcp_server.py",
        "changed": false,
        "lines_before": 6457,
        "lines_after": 6457,
        "lines_delta": 0,
        "functions_before": 11,
        "functions_after": 11,
        "functions_delta": 0,
        "lines_added": 0,
        "lines_removed": 0,
        "timestamp": 1772893751.5588486
      },
      {
        "file": "F:/BUREAU/turbo/src/mcp_server_sse.py",
        "changed": false,
        "lines_before": 511,
        "lines_after": 511,
        "lines_delta": 0,
        "functions_before": 3,
        "functions_after": 3,
        "functions_delta": 0,
        "lines_added": 0,
        "lines_removed": 0,
        "timestamp": 1772893751.5593495
      },
      {
        "file": "F:/BUREAU/turbo/src/memory_diagnostics.py",
        "changed": false,
        "lines_before": 129,
        "lines_after": 129,
        "lines_delta": 0,
        "functions_before": 6,
        "functions_after": 6,
        "functions_delta": 0,
        "lines_added": 0,
        "lines_removed": 0,
        "timestamp": 1772893751.5593495
      },
      {
        "file": "F:/BUREAU/turbo/src/metrics_aggregator.py",
        "changed": false,
        "lines_before": 176,
        "lines_after": 176,
        "lines_delta": 0,
        "functions_before": 6,
        "functions_after": 6,
        "functions_delta": 0,
        "lines_added": 0,
        "lines_removed": 0,
        "timestamp": 1772893751.5593495
      },
      {
        "file": "F:/BUREAU/turbo/src/network_adapter_manager.py",
        "changed": false,
        "lines_before": 115,
        "lines_after": 115,
        "lines_delta": 0,
        "functions_before": 7,
        "functions_after": 7,
        "functions_delta": 0,
        "lines_added": 0,
        "lines_removed": 0,
        "timestamp": 1772893751.5603564
      },
      {
        "file": "F:/BUREAU/turbo/src/network_monitor.py",
        "changed": false,
        "lines_before": 220,
        "lines_after": 220,
        "lines_delta": 0,
        "functions_before": 9,
        "functions_after": 9,
        "functions_delta": 0,
        "lines_added": 0,
        "lines_removed": 0,
        "timestamp": 1772893751.5603564
      },
      {
        "file": "F:/BUREAU/turbo/src/network_scanner.py",
        "changed": false,
        "lines_before": 221,
        "lines_after": 221,
        "lines_delta": 0,
        "functions_before": 11,
        "functions_after": 11,
        "functions_delta": 0,
        "lines_added": 0,
        "lines_removed": 0,
        "timestamp": 1772893751.5608623
      },
      {
        "file": "F:/BUREAU/turbo/src/notification_hub.py",
        "changed": false,
        "lines_before": 222,
        "lines_after": 222,
        "lines_delta": 0,
        "functions_before": 11,
        "functions_after": 11,
        "functions_delta": 0,
        "lines_added": 0,
        "lines_removed": 0,
        "timestamp": 1772893751.5608623
      },
      {
        "file": "F:/BUREAU/turbo/src/notification_manager.py",
        "changed": false,
        "lines_before": 182,
        "lines_after": 182,
        "lines_delta": 0,
        "functions_before": 12,
        "functions_after": 12,
        "functions_delta": 0,
        "lines_added": 0,
        "lines_removed": 0,
        "timestamp": 1772893751.5613627
      },
      {
        "file": "F:/BUREAU/turbo/src/notifier.py",
        "changed": false,
        "lines_before": 175,
        "lines_after": 175,
        "lines_delta": 0,
        "functions_before": 3,
        "functions_after": 3,
        "functions_delta": 0,
        "lines_added": 0,
        "lines_removed": 0,
        "timestamp": 1772893751.561861
      },
      {
        "file": "F:/BUREAU/turbo/src/openclaw_bridge.py",
        "changed": false,
        "lines_before": 366,
        "lines_after": 366,
        "lines_delta": 0,
        "functions_before": 14,
        "functions_after": 14,
        "functions_delta": 0,
        "lines_added": 0,
        "lines_removed": 0,
        "timestamp": 1772893751.561861
      },
      {
        "file": "F:/BUREAU/turbo/src/orchestrator.py",
        "changed": false,
        "lines_before": 1063,
        "lines_after": 1063,
        "lines_delta": 0,
        "functions_before": 4,
        "functions_after": 4,
        "functions_delta": 0,
        "lines_added": 0,
        "lines_removed": 0,
        "timestamp": 1772893751.563361
      },
      {
        "file": "F:/BUREAU/turbo/src/orchestrator_v2.py",
        "changed": false,
        "lines_before": 351,
        "lines_after": 351,
        "lines_delta": 0,
        "functions_before": 18,
        "functions_after": 18,
        "functions_delta": 0,
        "lines_added": 0,
        "lines_removed": 0,
        "timestamp": 1772893751.563861
      },
      {
        "file": "F:/BUREAU/turbo/src/output.py",
        "changed": false,
        "lines_before": 150,
        "lines_after": 150,
        "lines_delta": 0,
        "functions_before": 2,
        "functions_after": 2,
        "functions_delta": 0,
        "lines_added": 0,
        "lines_removed": 0,
        "timestamp": 1772893751.563861
      },
      {
        "file": "F:/BUREAU/turbo/src/pagefile_manager.py",
        "changed": false,
        "lines_before": 155,
        "lines_after": 155,
        "lines_delta": 0,
        "functions_before": 7,
        "functions_after": 7,
        "functions_delta": 0,
        "lines_added": 0,
        "lines_removed": 0,
        "timestamp": 1772893751.5643609
      },
      {
        "file": "F:/BUREAU/turbo/src/pattern_agents.py",
        "changed": false,
        "lines_before": 917,
        "lines_after": 917,
        "lines_delta": 0,
        "functions_before": 10,
        "functions_after": 10,
        "functions_delta": 0,
        "lines_added": 0,
        "lines_removed": 0,
        "timestamp": 1772893751.5653613
      },
      {
        "file": "F:/BUREAU/turbo/src/pattern_benchmark_runner.py",
        "changed": false,
        "lines_before": 323,
        "lines_after": 323,
        "lines_delta": 0,
        "functions_before": 6,
        "functions_after": 6,
        "functions_delta": 0,
        "lines_added": 0,
        "lines_removed": 0,
        "timestamp": 1772893751.5658612
      },
      {
        "file": "F:/BUREAU/turbo/src/pattern_discovery.py",
        "changed": false,
        "lines_before": 445,
        "lines_after": 445,
        "lines_delta": 0,
        "functions_before": 9,
        "functions_after": 9,
        "functions_delta": 0,
        "lines_added": 0,
        "lines_removed": 0,
        "timestamp": 1772893751.5663629
      },
      {
        "file": "F:/BUREAU/turbo/src/pattern_evolution.py",
        "changed": false,
        "lines_before": 350,
        "lines_after": 350,
        "lines_delta": 0,
        "functions_before": 13,
        "functions_after": 13,
        "functions_delta": 0,
        "lines_added": 0,
        "lines_removed": 0,
        "timestamp": 1772893751.5663629
      },
      {
        "file": "F:/BUREAU/turbo/src/pattern_lifecycle.py",
        "changed": false,
        "lines_before": 389,
        "lines_after": 389,
        "lines_delta": 0,
        "functions_before": 12,
        "functions_after": 12,
        "functions_delta": 0,
        "lines_added": 0,
        "lines_removed": 0,
        "timestamp": 1772893751.5668647
      },
      {
        "file": "F:/BUREAU/turbo/src/perfcounter.py",
        "changed": false,
        "lines_before": 166,
        "lines_after": 166,
        "lines_delta": 0,
        "functions_before": 9,
        "functions_after": 9,
        "functions_delta": 0,
        "lines_added": 0,
        "lines_removed": 0,
        "timestamp": 1772893751.5673635
      },
      {
        "file": "F:/BUREAU/turbo/src/performance_counter.py",
        "changed": false,
        "lines_before": 138,
        "lines_after": 138,
        "lines_delta": 0,
        "functions_before": 7,
        "functions_after": 7,
        "functions_delta": 0,
        "lines_added": 0,
        "lines_removed": 0,
        "timestamp": 1772893751.5673635
      },
      {
        "file": "F:/BUREAU/turbo/src/permission_manager.py",
        "changed": false,
        "lines_before": 147,
        "lines_after": 147,
        "lines_delta": 0,
        "functions_before": 12,
        "functions_after": 12,
        "functions_delta": 0,
        "lines_added": 0,
        "lines_removed": 0,
        "timestamp": 1772893751.5673635
      },
      {
        "file": "F:/BUREAU/turbo/src/perplexity_bridge.py",
        "changed": false,
        "lines_before": 286,
        "lines_after": 286,
        "lines_delta": 0,
        "functions_before": 2,
        "functions_after": 2,
        "functions_delta": 0,
        "lines_added": 0,
        "lines_removed": 0,
        "timestamp": 1772893751.5678613
      },
      {
        "file": "F:/BUREAU/turbo/src/pipeline_composer.py",
        "changed": false,
        "lines_before": 243,
        "lines_after": 243,
        "lines_delta": 0,
        "functions_before": 7,
        "functions_after": 7,
        "functions_delta": 0,
        "lines_added": 0,
        "lines_removed": 0,
        "timestamp": 1772893751.5678613
      },
      {
        "file": "F:/BUREAU/turbo/src/power_manager.py",
        "changed": false,
        "lines_before": 214,
        "lines_after": 214,
        "lines_delta": 0,
        "functions_before": 12,
        "functions_after": 12,
        "functions_delta": 0,
        "lines_added": 0,
        "lines_removed": 0,
        "timestamp": 1772893751.568363
      },
      {
        "file": "F:/BUREAU/turbo/src/power_plan_manager.py",
        "changed": false,
        "lines_before": 127,
        "lines_after": 127,
        "lines_delta": 0,
        "functions_before": 7,
        "functions_after": 7,
        "functions_delta": 0,
        "lines_added": 0,
        "lines_removed": 0,
        "timestamp": 1772893751.568363
      },
      {
        "file": "F:/BUREAU/turbo/src/prediction_engine.py",
        "changed": false,
        "lines_before": 269,
        "lines_after": 269,
        "lines_delta": 0,
        "functions_before": 8,
        "functions_after": 8,
        "functions_delta": 0,
        "lines_added": 0,
        "lines_removed": 0,
        "timestamp": 1772893751.5688617
      },
      {
        "file": "F:/BUREAU/turbo/src/printer_manager.py",
        "changed": false,
        "lines_before": 198,
        "lines_after": 198,
        "lines_delta": 0,
        "functions_before": 10,
        "functions_after": 10,
        "functions_delta": 0,
        "lines_added": 0,
        "lines_removed": 0,
        "timestamp": 1772893751.569361
      },
      {
        "file": "F:/BUREAU/turbo/src/proactive_agent.py",
        "changed": false,
        "lines_before": 370,
        "lines_after": 370,
        "lines_delta": 0,
        "functions_before": 8,
        "functions_after": 8,
        "functions_delta": 0,
        "lines_added": 0,
        "lines_removed": 0,
        "timestamp": 1772893751.569361
      },
      {
        "file": "F:/BUREAU/turbo/src/process_manager.py",
        "changed": false,
        "lines_before": 335,
        "lines_after": 335,
        "lines_delta": 0,
        "functions_before": 18,
        "functions_after": 18,
        "functions_delta": 0,
        "lines_added": 0,
        "lines_removed": 0,
        "timestamp": 1772893751.569361
      },
      {
        "file": "F:/BUREAU/turbo/src/quality_gate.py",
        "changed": false,
        "lines_before": 474,
        "lines_after": 474,
        "lines_delta": 0,
        "functions_before": 13,
        "functions_after": 13,
        "functions_delta": 0,
        "lines_added": 0,
        "lines_removed": 0,
        "timestamp": 1772893751.5703647
      },
      {
        "file": "F:/BUREAU/turbo/src/recycle_bin_manager.py",
        "changed": false,
        "lines_before": 113,
        "lines_after": 113,
        "lines_delta": 0,
        "functions_before": 7,
        "functions_after": 7,
        "functions_delta": 0,
        "lines_added": 0,
        "lines_removed": 0,
        "timestamp": 1772893751.5703647
      },
      {
        "file": "F:/BUREAU/turbo/src/reflection_engine.py",
        "changed": false,
        "lines_before": 502,
        "lines_after": 502,
        "lines_delta": 0,
        "functions_before": 14,
        "functions_after": 14,
        "functions_delta": 0,
        "lines_added": 0,
        "lines_removed": 0,
        "timestamp": 1772893751.5713701
      },
      {
        "file": "F:/BUREAU/turbo/src/registry_manager.py",
        "changed": false,
        "lines_before": 251,
        "lines_after": 251,
        "lines_delta": 0,
        "functions_before": 14,
        "functions_after": 14,
        "functions_delta": 0,
        "lines_added": 0,
        "lines_removed": 0,
        "timestamp": 1772893751.5713701
      },
      {
        "file": "F:/BUREAU/turbo/src/retry_manager.py",
        "changed": false,
        "lines_before": 192,
        "lines_after": 192,
        "lines_delta": 0,
        "functions_before": 11,
        "functions_after": 11,
        "functions_delta": 0,
        "lines_added": 0,
        "lines_removed": 0,
        "timestamp": 1772893751.571876
      },
      {
        "file": "F:/BUREAU/turbo/src/retry_policy.py",
        "changed": false,
        "lines_before": 176,
        "lines_after": 176,
        "lines_delta": 0,
        "functions_before": 12,
        "functions_after": 12,
        "functions_delta": 0,
        "lines_added": 0,
        "lines_removed": 0,
        "timestamp": 1772893751.5723763
      },
      {
        "file": "F:/BUREAU/turbo/src/routing_optimizer.py",
        "changed": false,
        "lines_before": 271,
        "lines_after": 271,
        "lines_delta": 0,
        "functions_before": 8,
        "functions_after": 8,
        "functions_delta": 0,
        "lines_added": 0,
        "lines_removed": 0,
        "timestamp": 1772893751.5723763
      },
      {
        "file": "F:/BUREAU/turbo/src/scenarios.py",
        "changed": false,
        "lines_before": 1598,
        "lines_after": 1598,
        "lines_delta": 0,
        "functions_before": 4,
        "functions_after": 4,
        "functions_delta": 0,
        "lines_added": 0,
        "lines_removed": 0,
        "timestamp": 1772893751.574373
      },
      {
        "file": "F:/BUREAU/turbo/src/scheduled_task_manager.py",
        "changed": false,
        "lines_before": 125,
        "lines_after": 125,
        "lines_delta": 0,
        "functions_before": 8,
        "functions_after": 8,
        "functions_delta": 0,
        "lines_added": 0,
        "lines_removed": 0,
        "timestamp": 1772893751.5748737
      },
      {
        "file": "F:/BUREAU/turbo/src/scheduler_manager.py",
        "changed": false,
        "lines_before": 171,
        "lines_after": 171,
        "lines_delta": 0,
        "functions_before": 10,
        "functions_after": 10,
        "functions_delta": 0,
        "lines_added": 0,
        "lines_removed": 0,
        "timestamp": 1772893751.5748737
      },
      {
        "file": "F:/BUREAU/turbo/src/screen_capture.py",
        "changed": false,
        "lines_before": 249,
        "lines_after": 249,
        "lines_delta": 0,
        "functions_before": 14,
        "functions_after": 14,
        "functions_delta": 0,
        "lines_added": 0,
        "lines_removed": 0,
        "timestamp": 1772893751.5753753
      },
      {
        "file": "F:/BUREAU/turbo/src/screen_resolution_manager.py",
        "changed": false,
        "lines_before": 113,
        "lines_after": 113,
        "lines_delta": 0,
        "functions_before": 7,
        "functions_after": 7,
        "functions_delta": 0,
        "lines_added": 0,
        "lines_removed": 0,
        "timestamp": 1772893751.5753753
      },
      {
        "file": "F:/BUREAU/turbo/src/security.py",
        "changed": false,
        "lines_before": 503,
        "lines_after": 503,
        "lines_delta": 0,
        "functions_before": 22,
        "functions_after": 22,
        "functions_delta": 0,
        "lines_added": 0,
        "lines_removed": 0,
        "timestamp": 1772893751.575874
      },
      {
        "file": "F:/BUREAU/turbo/src/self_improvement.py",
        "changed": false,
        "lines_before": 553,
        "lines_after": 553,
        "lines_delta": 0,
        "functions_before": 15,
        "functions_after": 15,
        "functions_delta": 0,
        "lines_added": 0,
        "lines_removed": 0,
        "timestamp": 1772893751.5768754
      },
      {
        "file": "F:/BUREAU/turbo/src/service_controller.py",
        "changed": false,
        "lines_before": 234,
        "lines_after": 234,
        "lines_delta": 0,
        "functions_before": 14,
        "functions_after": 14,
        "functions_delta": 0,
        "lines_added": 0,
        "lines_removed": 0,
        "timestamp": 1772893751.5768754
      },
      {
        "file": "F:/BUREAU/turbo/src/service_mesh.py",
        "changed": false,
        "lines_before": 183,
        "lines_after": 183,
        "lines_delta": 0,
        "functions_before": 15,
        "functions_after": 15,
        "functions_delta": 0,
        "lines_added": 0,
        "lines_removed": 0,
        "timestamp": 1772893751.577376
      },
      {
        "file": "F:/BUREAU/turbo/src/shadow_copy_manager.py",
        "changed": false,
        "lines_before": 115,
        "lines_after": 115,
        "lines_delta": 0,
        "functions_before": 7,
        "functions_after": 7,
        "functions_delta": 0,
        "lines_added": 0,
        "lines_removed": 0,
        "timestamp": 1772893751.577376
      },
      {
        "file": "F:/BUREAU/turbo/src/share_manager.py",
        "changed": false,
        "lines_before": 168,
        "lines_after": 168,
        "lines_delta": 0,
        "functions_before": 8,
        "functions_after": 8,
        "functions_delta": 0,
        "lines_added": 0,
        "lines_removed": 0,
        "timestamp": 1772893751.5778756
      },
      {
        "file": "F:/BUREAU/turbo/src/shortcut_manager.py",
        "changed": false,
        "lines_before": 225,
        "lines_after": 225,
        "lines_delta": 0,
        "functions_before": 14,
        "functions_after": 14,
        "functions_delta": 0,
        "lines_added": 0,
        "lines_removed": 0,
        "timestamp": 1772893751.5778756
      },
      {
        "file": "F:/BUREAU/turbo/src/signal_formatter.py",
        "changed": false,
        "lines_before": 156,
        "lines_after": 156,
        "lines_delta": 0,
        "functions_before": 7,
        "functions_after": 7,
        "functions_delta": 0,
        "lines_added": 0,
        "lines_removed": 0,
        "timestamp": 1772893751.5778756
      },
      {
        "file": "F:/BUREAU/turbo/src/skills.py",
        "changed": false,
        "lines_before": 1753,
        "lines_after": 1753,
        "lines_delta": 0,
        "functions_before": 17,
        "functions_after": 17,
        "functions_delta": 0,
        "lines_added": 0,
        "lines_removed": 0,
        "timestamp": 1772893751.580385
      },
      {
        "file": "F:/BUREAU/turbo/src/smart_dispatcher.py",
        "changed": false,
        "lines_before": 351,
        "lines_after": 351,
        "lines_delta": 0,
        "functions_before": 8,
        "functions_after": 8,
        "functions_delta": 0,
        "lines_added": 0,
        "lines_removed": 0,
        "timestamp": 1772893751.5808845
      },
      {
        "file": "F:/BUREAU/turbo/src/smart_retry.py",
        "changed": false,
        "lines_before": 188,
        "lines_after": 188,
        "lines_delta": 0,
        "functions_before": 11,
        "functions_after": 11,
        "functions_delta": 0,
        "lines_added": 0,
        "lines_removed": 0,
        "timestamp": 1772893751.5813854
      },
      {
        "file": "F:/BUREAU/turbo/src/startup_manager.py",
        "changed": false,
        "lines_before": 210,
        "lines_after": 210,
        "lines_delta": 0,
        "functions_before": 13,
        "functions_after": 13,
        "functions_delta": 0,
        "lines_added": 0,
        "lines_removed": 0,
        "timestamp": 1772893751.5818837
      },
      {
        "file": "F:/BUREAU/turbo/src/state_machine.py",
        "changed": false,
        "lines_before": 138,
        "lines_after": 138,
        "lines_delta": 0,
        "functions_before": 15,
        "functions_after": 15,
        "functions_delta": 0,
        "lines_added": 0,
        "lines_removed": 0,
        "timestamp": 1772893751.5818837
      },
      {
        "file": "F:/BUREAU/turbo/src/storage_pool_manager.py",
        "changed": false,
        "lines_before": 131,
        "lines_after": 131,
        "lines_delta": 0,
        "functions_before": 6,
        "functions_after": 6,
        "functions_delta": 0,
        "lines_added": 0,
        "lines_removed": 0,
        "timestamp": 1772893751.5823836
      },
      {
        "file": "F:/BUREAU/turbo/src/sysrestore_manager.py",
        "changed": false,
        "lines_before": 122,
        "lines_after": 122,
        "lines_delta": 0,
        "functions_before": 8,
        "functions_after": 8,
        "functions_delta": 0,
        "lines_added": 0,
        "lines_removed": 0,
        "timestamp": 1772893751.5823836
      },
      {
        "file": "F:/BUREAU/turbo/src/system_info_collector.py",
        "changed": false,
        "lines_before": 207,
        "lines_after": 207,
        "lines_delta": 0,
        "functions_before": 9,
        "functions_after": 9,
        "functions_delta": 0,
        "lines_added": 0,
        "lines_removed": 0,
        "timestamp": 1772893751.5828836
      },
      {
        "file": "F:/BUREAU/turbo/src/system_profiler.py",
        "changed": false,
        "lines_before": 240,
        "lines_after": 240,
        "lines_delta": 0,
        "functions_before": 13,
        "functions_after": 13,
        "functions_delta": 0,
        "lines_added": 0,
        "lines_removed": 0,
        "timestamp": 1772893751.5828836
      },
      {
        "file": "F:/BUREAU/turbo/src/task_queue.py",
        "changed": false,
        "lines_before": 312,
        "lines_after": 312,
        "lines_delta": 0,
        "functions_before": 14,
        "functions_after": 14,
        "functions_delta": 0,
        "lines_added": 0,
        "lines_removed": 0,
        "timestamp": 1772893751.5833867
      },
      {
        "file": "F:/BUREAU/turbo/src/time_sync_manager.py",
        "changed": false,
        "lines_before": 176,
        "lines_after": 176,
        "lines_delta": 0,
        "functions_before": 11,
        "functions_after": 11,
        "functions_delta": 0,
        "lines_added": 0,
        "lines_removed": 0,
        "timestamp": 1772893751.5838842
      },
      {
        "file": "F:/BUREAU/turbo/src/tools.py",
        "changed": false,
        "lines_before": 2616,
        "lines_after": 2616,
        "lines_delta": 0,
        "functions_before": 66,
        "functions_after": 66,
        "functions_delta": 0,
        "lines_added": 0,
        "lines_removed": 0,
        "timestamp": 1772893751.586384
      },
      {
        "file": "F:/BUREAU/turbo/src/trading.py",
        "changed": false,
        "lines_before": 506,
        "lines_after": 506,
        "lines_delta": 0,
        "functions_before": 14,
        "functions_after": 14,
        "functions_delta": 0,
        "lines_added": 0,
        "lines_removed": 0,
        "timestamp": 1772893751.586884
      },
      {
        "file": "F:/BUREAU/turbo/src/trading_engine.py",
        "changed": false,
        "lines_before": 339,
        "lines_after": 339,
        "lines_delta": 0,
        "functions_before": 12,
        "functions_after": 12,
        "functions_delta": 0,
        "lines_added": 0,
        "lines_removed": 0,
        "timestamp": 1772893751.5873878
      },
      {
        "file": "F:/BUREAU/turbo/src/trading_sentinel.py",
        "changed": false,
        "lines_before": 252,
        "lines_after": 252,
        "lines_delta": 0,
        "functions_before": 3,
        "functions_after": 3,
        "functions_delta": 0,
        "lines_added": 0,
        "lines_removed": 0,
        "timestamp": 1772893751.5878842
      },
      {
        "file": "F:/BUREAU/turbo/src/tts_streaming.py",
        "changed": false,
        "lines_before": 209,
        "lines_after": 209,
        "lines_delta": 0,
        "functions_before": 6,
        "functions_after": 6,
        "functions_delta": 0,
        "lines_added": 0,
        "lines_removed": 0,
        "timestamp": 1772893751.5878842
      },
      {
        "file": "F:/BUREAU/turbo/src/usb_device_manager.py",
        "changed": false,
        "lines_before": 113,
        "lines_after": 113,
        "lines_delta": 0,
        "functions_before": 7,
        "functions_after": 7,
        "functions_delta": 0,
        "lines_added": 0,
        "lines_removed": 0,
        "timestamp": 1772893751.5878842
      },
      {
        "file": "F:/BUREAU/turbo/src/usb_monitor.py",
        "changed": false,
        "lines_before": 196,
        "lines_after": 196,
        "lines_delta": 0,
        "functions_before": 10,
        "functions_after": 10,
        "functions_delta": 0,
        "lines_added": 0,
        "lines_removed": 0,
        "timestamp": 1772893751.588384
      },
      {
        "file": "F:/BUREAU/turbo/src/user_account_manager.py",
        "changed": false,
        "lines_before": 146,
        "lines_after": 146,
        "lines_delta": 0,
        "functions_before": 8,
        "functions_after": 8,
        "functions_delta": 0,
        "lines_added": 0,
        "lines_removed": 0,
        "timestamp": 1772893751.588384
      },
      {
        "file": "F:/BUREAU/turbo/src/vad.py",
        "changed": false,
        "lines_before": 272,
        "lines_after": 272,
        "lines_delta": 0,
        "functions_before": 11,
        "functions_after": 11,
        "functions_delta": 0,
        "lines_added": 0,
        "lines_removed": 0,
        "timestamp": 1772893751.5888839
      },
      {
        "file": "F:/BUREAU/turbo/src/virtual_desktop.py",
        "changed": false,
        "lines_before": 144,
        "lines_after": 144,
        "lines_delta": 0,
        "functions_before": 8,
        "functions_after": 8,
        "functions_delta": 0,
        "lines_added": 0,
        "lines_removed": 0,
        "timestamp": 1772893751.5888839
      },
      {
        "file": "F:/BUREAU/turbo/src/virtual_memory_manager.py",
        "changed": false,
        "lines_before": 131,
        "lines_after": 131,
        "lines_delta": 0,
        "functions_before": 6,
        "functions_after": 6,
        "functions_delta": 0,
        "lines_added": 0,
        "lines_removed": 0,
        "timestamp": 1772893751.5888839
      },
      {
        "file": "F:/BUREAU/turbo/src/voice.py",
        "changed": false,
        "lines_before": 727,
        "lines_after": 727,
        "lines_delta": 0,
        "functions_before": 17,
        "functions_after": 17,
        "functions_delta": 0,
        "lines_added": 0,
        "lines_removed": 0,
        "timestamp": 1772893751.5898874
      },
      {
        "file": "F:/BUREAU/turbo/src/voice_correction.py",
        "changed": false,
        "lines_before": 2399,
        "lines_after": 2399,
        "lines_delta": 0,
        "functions_before": 25,
        "functions_after": 25,
        "functions_delta": 0,
        "lines_added": 0,
        "lines_removed": 0,
        "timestamp": 1772893751.5918922
      },
      {
        "file": "F:/BUREAU/turbo/src/volume_manager.py",
        "changed": false,
        "lines_before": 153,
        "lines_after": 153,
        "lines_delta": 0,
        "functions_before": 8,
        "functions_after": 8,
        "functions_delta": 0,
        "lines_added": 0,
        "lines_removed": 0,
        "timestamp": 1772893751.592392
      },
      {
        "file": "F:/BUREAU/turbo/src/webhook_manager.py",
        "changed": false,
        "lines_before": 179,
        "lines_after": 179,
        "lines_delta": 0,
        "functions_before": 12,
        "functions_after": 12,
        "functions_delta": 0,
        "lines_added": 0,
        "lines_removed": 0,
        "timestamp": 1772893751.5928936
      },
      {
        "file": "F:/BUREAU/turbo/src/wifi_manager.py",
        "changed": false,
        "lines_before": 230,
        "lines_after": 230,
        "lines_delta": 0,
        "functions_before": 10,
        "functions_after": 10,
        "functions_delta": 0,
        "lines_added": 0,
        "lines_removed": 0,
        "timestamp": 1772893751.5928936
      },
      {
        "file": "F:/BUREAU/turbo/src/window_manager.py",
        "changed": false,
        "lines_before": 228,
        "lines_after": 228,
        "lines_delta": 0,
        "functions_before": 14,
        "functions_after": 14,
        "functions_delta": 0,
        "lines_added": 0,
        "lines_removed": 0,
        "timestamp": 1772893751.5933924
      },
      {
        "file": "F:/BUREAU/turbo/src/windows.py",
        "changed": false,
        "lines_before": 597,
        "lines_after": 597,
        "lines_delta": 0,
        "functions_before": 54,
        "functions_after": 54,
        "functions_delta": 0,
        "lines_added": 0,
        "lines_removed": 0,
        "timestamp": 1772893751.593892
      },
      {
        "file": "F:/BUREAU/turbo/src/windows_event_log_reader.py",
        "changed": false,
        "lines_before": 123,
        "lines_after": 123,
        "lines_delta": 0,
        "functions_before": 8,
        "functions_after": 8,
        "functions_delta": 0,
        "lines_added": 0,
        "lines_removed": 0,
        "timestamp": 1772893751.594392
      },
      {
        "file": "F:/BUREAU/turbo/src/windows_feature_manager.py",
        "changed": false,
        "lines_before": 135,
        "lines_after": 135,
        "lines_delta": 0,
        "functions_before": 10,
        "functions_after": 10,
        "functions_delta": 0,
        "lines_added": 0,
        "lines_removed": 0,
        "timestamp": 1772893751.594392
      },
      {
        "file": "F:/BUREAU/turbo/src/windows_update_manager.py",
        "changed": false,
        "lines_before": 138,
        "lines_after": 138,
        "lines_delta": 0,
        "functions_before": 7,
        "functions_after": 7,
        "functions_delta": 0,
        "lines_added": 0,
        "lines_removed": 0,
        "timestamp": 1772893751.594892
      },
      {
        "file": "F:/BUREAU/turbo/src/wmi_explorer.py",
        "changed": false,
        "lines_before": 167,
        "lines_after": 167,
        "lines_delta": 0,
        "functions_before": 8,
        "functions_after": 8,
        "functions_delta": 0,
        "lines_added": 0,
        "lines_removed": 0,
        "timestamp": 1772893751.594892
      },
      {
        "file": "F:/BUREAU/turbo/src/workflow_engine.py",
        "changed": false,
        "lines_before": 324,
        "lines_after": 324,
        "lines_delta": 0,
        "functions_before": 10,
        "functions_after": 10,
        "functions_delta": 0,
        "lines_added": 0,
        "lines_removed": 0,
        "timestamp": 1772893751.595392
      }
    ]
  },
  "dry_run": true
}