[
  {
    "symbol": "BTC",
    "trend": "RANGE",
    "direction": "NEUTRE",
    "score": 0,
    "last_price": 68405.1,
    "change_24h": 1.54,
    "volume_24h": 2111298620.36358,
    "funding_rate": -8e-06,
    "rsi": 64.90921155818288,
    "momentum_1h": 0.19745071788277013,
    "momentum_4h": 0.8596030786470467,
    "vol_ratio": 0.46250934495861035,
    "range_pos": 60.87038968427058,
    "entry": 0,
    "tp": 0,
    "sl": 0,
    "signals": []
  },
  {
    "symbol": "ETH",
    "trend": "RANGE",
    "direction": "NEUTRE",
    "score": 0,
    "last_price": 2066.84,
    "change_24h": 2.68,
    "volume_24h": 884143420.1132,
    "funding_rate": -2e-05,
    "rsi": 68.1967752550182,
    "momentum_1h": 0.24687765247969665,
    "momentum_4h": 1.2680307306365686,
    "vol_ratio": 0.39472884435637445,
    "range_pos": 63.74722838137503,
    "entry": 0,
    "tp": 0,
    "sl": 0,
    "signals": []
  },
  {
    "symbol": "SOL",
    "trend": "RANGE",
    "direction": "NEUTRE",
    "score": 0,
    "last_price": 87.7,
    "change_24h": 2.0500000000000003,
    "volume_24h": 2208486104.472,
    "funding_rate": 7.2e-05,
    "rsi": 50.81967213114757,
    "momentum_1h": 0.09130335539830894,
    "momentum_4h": 0.11415525114156226,
    "vol_ratio": 0.43436930286015785,
    "range_pos": 26.943005181347047,
    "entry": 0,
    "tp": 0,
    "sl": 0,
    "signals": []
  },
  {
    "symbol": "SUI",
    "trend": "RANGE",
    "direction": "NEUTRE",
    "score": 0,
    "last_price": 0.9578,
    "change_24h": 1.1400000000000001,
    "volume_24h": 243410443.5349,
    "funding_rate": 8.5e-05,
    "rsi": 52.028639618138456,
    "momentum_1h": -0.03131197161047563,
    "momentum_4h": 0.7680168332456574,
    "vol_ratio": 0.2139772853647104,
    "range_pos": 32.846715328467205,
    "entry": 0,
    "tp": 0,
    "sl": 0,
    "signals": []
  },
  {
    "symbol": "PEPE",
    "trend": "RANGE",
    "direction": "NEUTRE",
    "score": 0,
    "last_price": 4.074e-06,
    "change_24h": -2.58,
    "volume_24h": 257626328.57,
    "funding_rate": 0.0001,
    "rsi": 54.33526011560714,
    "momentum_1h": -0.14705882352940206,
    "momentum_4h": 0.716934487021015,
    "vol_ratio": 0.46851385390428213,
    "range_pos": 37.037037037037294,
    "entry": 0,
    "tp": 0,
    "sl": 0,
    "signals": []
  },
  {
    "symbol": "DOGE",
    "trend": "RANGE",
    "direction": "NEUTRE",
    "score": 0,
    "last_price": 0.10022,
    "change_24h": -1.28,
    "volume_24h": 668840957.82,
    "funding_rate": 3.2e-05,
    "rsi": 48.35680751173707,
    "momentum_1h": 0.18994301709488115,
    "momentum_4h": 0.029943108094622462,
    "vol_ratio": 0.09689148033934979,
    "range_pos": 30.693069306931044,
    "entry": 0,
    "tp": 0,
    "sl": 0,
    "signals": []
  },
  {
    "symbol": "XRP",
    "trend": "RANGE",
    "direction": "NEUTRE",
    "score": 0,
    "last_price": 1.447,
    "change_24h": 0.43,
    "volume_24h": 820121090.6435,
    "funding_rate": -2.6e-05,
    "rsi": 69.7115384615385,
    "momentum_1h": 0.1522702104097439,
    "momentum_4h": 1.901408450704235,
    "vol_ratio": 1.082175313484374,
    "range_pos": 58.25049701789283,
    "entry": 0,
    "tp": 0,
    "sl": 0,
    "signals": []
  },
  {
    "symbol": "ADA",
    "trend": "RANGE",
    "direction": "NEUTRE",
    "score": 0,
    "last_price": 0.295,
    "change_24h": 1.6099999999999999,
    "volume_24h": 285637958.9787,
    "funding_rate": 0.0001,
    "rsi": 46.39999999999997,
    "momentum_1h": 0.34013605442176903,
    "momentum_4h": -0.03388681802778346,
    "vol_ratio": 0.1299861029074879,
    "range_pos": 31.50684931506818,
    "entry": 0,
    "tp": 0,
    "sl": 0,
    "signals": []
  },
  {
    "symbol": "AVAX",
    "trend": "RANGE",
    "direction": "NEUTRE",
    "score": 0,
    "last_price": 9.427,
    "change_24h": -1.06,
    "volume_24h": 176983316.5897,
    "funding_rate": 0.0001,
    "rsi": 46.278317152103625,
    "momentum_1h": -0.09537939805002481,
    "momentum_4h": -0.15886464732048897,
    "vol_ratio": 0.49025675612029596,
    "range_pos": 14.285714285714127,
    "entry": 0,
    "tp": 0,
    "sl": 0,
    "signals": []
  },
  {
    "symbol": "LINK",
    "trend": "RANGE",
    "direction": "NEUTRE",
    "score": 0,
    "last_price": 9.297,
    "change_24h": 0.19,
    "volume_24h": 116487443.3188,
    "funding_rate": 0.0001,
    "rsi": 66.66666666666684,
    "momentum_1h": 0.6713589604764609,
    "momentum_4h": 1.5288850060063401,
    "vol_ratio": 0.4380399050157866,
    "range_pos": 80.52631578947414,
    "entry": 0,
    "tp": 0,
    "sl": 0,
    "signals": []
  }
]